{
  "title": "header",
  "titleText": "headerText",
  "file": "components/VBadge",
  "children": [
    {
      "type": "section",
      "children": [
        {
          "type": "usage",
          "value": "usage"
        }
      ]
    },
    {
      "type": "section",
      "children": [
        {
          "type": "api",
          "value": ["v-badge"]
        }
      ]
    },
    {
      "type": "section",
      "children": [
        {
          "type": "playground",
          "value": "playground"
        }
      ]
    },
    {
      "type": "section",
      "children": [
        {
          "type": "examples",
          "value": [
            "simple/bottom",
            "simple/left",
            "simple/overlap",
            "simple/icon",
            "simple/inline",
            "simple/visibility",
            "intermediate/hover",
            "complex/dynamic"
          ]
        }
      ]
    },
    {
      "type": "section",
      "children": [
        {
          "type": "up-next",
          "value": [
            "components/avatars",
            "components/icons",
            "components/toolbars"
          ]
        }
      ]
    }
  ]
}
