{
  "title": "header",
  "titleText": "headerText",
  "file": "components/VChip",
  "mdSpec": {
    "version": "2",
    "link": "https://material.io/design/components/chips.html"
  },
  "children": [
    {
      "type": "section",
      "children": [
        {
          "type": "usage",
          "value": "usage"
        }
      ]
    },
    {
      "type": "section",
      "children": [
        {
          "type": "api",
          "value": ["v-chip"]
        }
      ]
    },
    {
      "type": "section",
      "children": [
        {
          "type": "playground",
          "value": "playground"
        }
      ]
    },
    {
      "type": "section",
      "children": [
        {
          "type": "examples",
          "value": [
            "simple/colored",
            "simple/icon",
            "simple/outlined",
            "simple/label",
            "simple/sizes",
            "simple/draggable",
            "simple/filter",
            "simple/no-ripple",
            "intermediate/closable",
            "intermediate/action-chips",
            "intermediate/in-selects",
            "complex/photos",
            "complex/filtering",
            "complex/expandable"
          ]
        }
      ]
    },
    {
      "type": "section",
      "children": [
        {
          "type": "up-next",
          "value": [
            "components/avatars",
            "components/icons",
            "components/selects"
          ]
        }
      ]
    }
  ]
}
