{
  "title": "header",
  "titleText": "headerText",
  "file": "components/VDataTable",
  "mdSpec": {
    "version": "2",
    "link": "https://material.io/design/components/data-tables.html"
  },
  "children": [
    {
      "type": "section",
      "children": [
        {
          "type": "usage",
          "value": "usage"
        }
      ]
    },
    {
      "type": "section",
      "children": [
        {
          "type": "api",
          "value": [
            "v-data-table",
            "v-edit-dialog"
          ]
        }
      ]
    },
    {
      "type": "section",
      "children": [
        {
          "type": "examples",
          "value": [
            "slots",
            "select",
            "expand",
            "group",
            "multi-sort",
            "search",
            "customize-header",
            "customize-rows",
            "customize-footer",
            "paginate",
            "sort",
            "server",
            "headerless",
            "edit-dialog",
            "crud",
            "virtualized"
          ]
        }
      ]
    },
    {
      "type": "section",
      "children": [
        {
          "type": "up-next",
          "value": [
            "components/data-iterator",
            "components/paginations",
            "components/lists"
          ]
        }
      ]
    }
  ]
}
